leandropls/easylambda/__init__.py
leandropls/easylambda/aws.py
leandropls/easylambda/body.py
leandropls/easylambda/dependency.py
leandropls/easylambda/depends.py
leandropls/easylambda/errors.py
leandropls/easylambda/header.py
leandropls/easylambda/main.py
leandropls/easylambda/method_router.py
leandropls/easylambda/path.py
leandropls/easylambda/query.py
leandropls_easylambda-0.1.3.dist-info/LICENSE
leandropls_easylambda-0.1.3.dist-info/METADATA
leandropls_easylambda-0.1.3.dist-info/WHEEL
leandropls_easylambda-0.1.3.dist-info/RECORD
