Metadata-Version: 2.1
Name: leandropls.easylambda
Version: 0.1.3
Summary: 
License: MIT
Author: Leandro Lima
Author-email: leandro@lls-software.com
Requires-Python: >=3.12,<4.0
Classifier: License :: OSI Approved :: MIT License
Classifier: Programming Language :: Python :: 3
Classifier: Programming Language :: Python :: 3.12
Requires-Dist: pydantic (>=2.9.2,<3.0.0)
